pong_atari/__init__.py
pong_atari/ball.py
pong_atari/main.py
pong_atari/meta.py
pong_atari/player.py
pong_atari/pong.py
pong_atari/data/gfx/atari.otf
pong_atari/data/gfx/logo.png
pong_atari/data/sfx/paddle.wav
pong_atari/data/sfx/score.wav
pong_atari/data/sfx/wall.wav
pong_atari-2.1.2.dist-info/METADATA
pong_atari-2.1.2.dist-info/WHEEL
pong_atari-2.1.2.dist-info/entry_points.txt
pong_atari-2.1.2.dist-info/licenses/LICENSE
pong_atari-2.1.2.dist-info/RECORD
