Metadata-Version: 2.1
Name: pong-atari
Version: 2.1.2
Summary: Pong written using pygame
Project-URL: Homepage, https://github.com/jacob-thompson/pong-atari
Project-URL: Bug Reports, https://github.com/jacob-thompson/pong-atari/issues
Author-email: "Jacob A. Thompson" <jacobalthompson@gmail.com>
Maintainer-email: "Jacob A. Thompson" <jacobalthompson@gmail.com>
License: MIT License
License-File: LICENSE
Keywords: application,atari,executable,game,pong
Classifier: Development Status :: 5 - Production/Stable
Classifier: License :: OSI Approved :: MIT License
Classifier: Programming Language :: Python :: 3
Classifier: Programming Language :: Python :: 3 :: Only
Classifier: Programming Language :: Python :: 3.7
Classifier: Programming Language :: Python :: 3.8
Classifier: Programming Language :: Python :: 3.9
Classifier: Programming Language :: Python :: 3.10
Classifier: Topic :: Games/Entertainment
Requires-Python: >=3.7
Requires-Dist: pygame
